gonb/__init__.py
gonb/__main__.py
gonb/admin_user.py
gonb/exceptions.py
gonb/folder.py
gonb/grafana.py
gonb/organisation_transfer.py
gonb/organization.py
gonb/provider.py
gonb/team.py
gonb/user.py
json_gonb_provider/__init__.py
json_gonb_provider/__main__.py
json_gonb_provider/json_file.py
json_team_gonb_provider/__init__.py
json_team_gonb_provider/__main__.py
json_team_gonb_provider/json_file.py
okta_gonb_provider/__init__.py
okta_gonb_provider/__main__.py
okta_gonb_provider/okta.py
tests/__init__.py
tests/test_admin_user.py
tests/test_diff.py
tests/test_user.py
gonb-0.6.1.dist-info/LICENSE
gonb-0.6.1.dist-info/METADATA
gonb-0.6.1.dist-info/NOTICE
gonb-0.6.1.dist-info/WHEEL
gonb-0.6.1.dist-info/top_level.txt
gonb-0.6.1.dist-info/RECORD
