Metadata-Version: 2.1
Name: gonb
Version: 0.6.1
Summary: A Grafana onboarding tool
Home-page: https://github.com/thenodon/gonb
Author: thenodon
Author-email: aha@ingby.co,
License: Apache Software License (http://www.apache.org/licenses/LICENSE-2.0)
Requires-Python: >=3.8
License-File: LICENSE
License-File: NOTICE
Requires-Dist: requests ~=2.28.2
Requires-Dist: urllib3
Requires-Dist: logfmter ~=0.0.6
